feast_mysql/__init__.py
feast_mysql/mysql_config.py
feast_mysql/registry_store.py
feast_mysql/type_map.py
feast_mysql/utils.py
feast_mysql/offline_store/__init__.py
feast_mysql/offline_store/mysql.py
feast_mysql/offline_store/mysql_source.py
feast_mysql-0.3.3.dist-info/METADATA
feast_mysql-0.3.3.dist-info/WHEEL
feast_mysql-0.3.3.dist-info/top_level.txt
feast_mysql-0.3.3.dist-info/RECORD
