Metadata-Version: 2.1
Name: feast-mysql
Version: 0.3.3
Summary: MySQL registry and offline store for Feast
Home-page: https://github.com/shaped-ai/feast-mysql
Author: Shaped
Author-email: shai@shaped.ai
License: Apache License, Version 2.0
Project-URL: Bug Tracker, https://github.com/shaped-ai/feast-mysql/issues
Keywords: feast featurestore mysql offlinestore
Platform: UNKNOWN
Classifier: License :: OSI Approved :: Apache Software License
Classifier: Programming Language :: Python
Classifier: Programming Language :: Python :: 3
Classifier: Programming Language :: Python :: 3.7
Classifier: Programming Language :: Python :: 3.8
Classifier: Programming Language :: Python :: 3.9
Requires-Python: >=3.7.0
Requires-Dist: feast (==0.19.*)
Requires-Dist: mysql-connector-python (==8.0.28)
Requires-Dist: pyarrow (>=2.0.0)
Provides-Extra: dev
Requires-Dist: flake8 ; extra == 'dev'
Requires-Dist: black (==21.10b0) ; extra == 'dev'
Requires-Dist: isort (>=5) ; extra == 'dev'
Requires-Dist: mypy (==0.790) ; extra == 'dev'
Requires-Dist: build (==0.7.0) ; extra == 'dev'
Requires-Dist: twine (==3.4.2) ; extra == 'dev'
Requires-Dist: pytest (>=6.0.0) ; extra == 'dev'
